np2mcpl.cpython-38-i386-linux-gnu.so
np2mcpl.libs/libmcpl-8786a355.so
np2mcpl-0.0.1.dist-info/RECORD
np2mcpl-0.0.1.dist-info/LICENSE
np2mcpl-0.0.1.dist-info/METADATA
np2mcpl-0.0.1.dist-info/WHEEL
np2mcpl-0.0.1.dist-info/top_level.txt
