Metadata-Version: 2.1
Name: np2mcpl
Version: 0.0.1
Summary: Package to convert a Monte Carlo particle in the form of a numpy-array to a MCPL-file.
Author-email: Erik B Knudsen <erik.knudsen@copenhagenatomics.com>
Project-URL: Homepage, https://github.com/ebknudsen/np2mcpl
Project-URL: Bug Tracker, https://github.com/ebknudsen/np2mcpl/issues
Classifier: Programming Language :: Python :: 3
Classifier: License :: OSI Approved :: MIT License
Classifier: Operating System :: OS Independent
Requires-Python: >=3.8
License-File: LICENSE
